cnncc/__init__.py
cnncc/main.py
cnncc/utils.py
cnncc/models/__init__.py
cnncc/models/logreg/__init__.py
cnncc/models/logreg/logreg.py
cnncc/models/logreg/model_12_61.joblib
cnncc/models/logreg/model_2_64.joblib
cnncc/models/logreg/model_raw_66.joblib
cnncc/models/nagao/__init__.py
cnncc/models/nagao/nagao.py
cnncc/models/nagao/nagao_71acc.pt
cnncc/models/paper/__init__.py
cnncc/models/resnet/__init__.py
cnncc/models/resnet/model.py
cnncc/models/resnet/model1.pt
cnncc/models/resnet/model1_state.pth
cnncc-1.1.4.dist-info/METADATA
cnncc-1.1.4.dist-info/WHEEL
cnncc-1.1.4.dist-info/entry_points.txt
cnncc-1.1.4.dist-info/top_level.txt
cnncc-1.1.4.dist-info/RECORD
